Digital/Textbooks/Principles_And_Practices_Of_Interconnection_Networks/ch2/2-3/allocator.sv
// // allocator.sv
// //
// of input phit and current field of routing header
// //
// once assigned, holds a port for the duration of a packet
// //
// as long as payload phits are on input).
// //
// uses fixed priority arbitration (r0 is highest).

module allocator(input logic clk,
                 input logic [1:0] thisPort,
                 input logic [3:0] r0, r1, r2, r3,
                 output logic [3:0] select,
                 output logic shift);

  logic [3:0] grant, head, payload, match, request, hold;
  logic [2:0] pass;
  logic avail;
  logic [3:0] last;

  assign head = {r3[3:2]==3, r2[3:2]==3, r1[3:2]==3, r0[3:2]==3};
  assign payload = {r3[3:2]==2, r2[3:2]==2, r1[3:2]==2, r0[3:2]==2};
  assign match = {r3[1:0]==thisPort, r2[1:0]==thisPort,
                  r1[1:0]==thisPort, r0[1:0]==thisPort};
  assign request = head & match;
  assign pass = {pass[1:0], avail} & ~request[2:0];
  assign grant = request & {pass, avail};
  assign hold = last & payload;
  assign select = grant | hold;
  assign avail = ~(|hold);
  assign shift = |grant;
    always @(posedge clk) begin
        last <= select;
    end

    initial begin
        $dumpfile("allocator.vcd"); // Specify filename
        $dumpvars(0, allocator); // Dump all signals within the scope of my_design
        #1; // Wait a small amount of time to ensure dump starts
    end
endmodule

Digital/Textbooks/Principles_And_Practices_Of_Interconnection_Networks/ch2/2-3/allocator.vcd
$date
	Sat Aug 16 11:15:47 2025
$end
$version
	Icarus Verilog
$end
$timescale
	1ps
$end
$scope module allocator $end
$var wire 1 ! avail $end
$var wire 1 " clk $end
$var wire 4 # grant [3:0] $end
$var wire 4 $ hold [3:0] $end
$var wire 3 % pass [2:0] $end
$var wire 4 & r0 [3:0] $end
$var wire 4 ' r1 [3:0] $end
$var wire 4 ( r2 [3:0] $end
$var wire 4 ) r3 [3:0] $end
$var wire 4 * request [3:0] $end
$var wire 4 + select [3:0] $end
$var wire 2 , thisPort [1:0] $end
$var wire 1 - shift $end
$var wire 4 . payload [3:0] $end
$var wire 4 / match [3:0] $end
$var wire 4 0 head [3:0] $end
$var reg 4 1 last [3:0] $end
$upscope $end
$enddefinitions $end
$comment Show the parameter values. $end
$dumpall
$end
#0
$dumpvars
bx 1
b0 0
b1111 /
b0 .
0-
b0 ,
b0 +
b0 *
b0 )
b0 (
b0 '
b0 &
b111 %
b0 $
b0 #
1"
1!
$end
#5000
b0 %
b1 +
1-
b1 #
b101 *
b111 /
b1101 0
b1111 )
b1100 (
b1100 &
0"
#10000
0-
b0 #
0!
b0 *
b1 $
b1111 /
b0 0
b1101 .
b1000 )
b1000 (
b1000 &
b1 1
1"
#15000
0"
#20000
1"
#25000
0"
#30000
b10 *
b10 0
b1100 '
1"
#35000
0"
#40000
b0 *
b0 0
b1111 .
b1000 '
1"
#45000
0"
#50000
1"
#55000
0"
#60000
1"
#65000
0"
#70000
1"
#75000
0"
#80000
1"
#85000
0"
#90000
1"
#95000
0"
#100000
1"
#105000
0"
#110000
1"
#115000
0"
#120000
1"
#125000
0"
#130000
1"
#135000
0"
#140000
b1000 0
b111 .
b111 /
b1101 )
1"
#145000
0"
#150000
b111 %
b0 +
1!
b0 $
b1 0
b1110 .
b1110 /
b1000 )
b1110 &
1"
#155000
0"
#160000
b0 0
b1111 .
b1111 /
b1000 &
b0 1
1"
#165000
0"
#170000
1"
#175000
0"
#180000
1"
#185000
0"
#190000
1"
#195000
0"
#200000
1"
#205000
0"
#210000
1"
#215000
0"
#220000
1"
#225000
0"
#230000
b100 0
b1011 .
b1011 /
b1111 (
1"
#235000
0"
#240000
b0 0
b1111 .
b1111 /
b1000 (
1"
#245000
0"
#250000
1"
#255000
0"
#260000
1"
#265000
0"
#270000
b1000 0
b111 .
b111 /
b1111 )
1"
#275000
0"
#280000
b0 0
b1111 .
b1111 /
b1000 )
1"
#285000
0"
#290000
1"
#295000
0"
#300000
b1101 .
b0 '
1"
#305000
0"
#310000
b10 0
b1101 /
b1111 '
1"
#315000
0"
#320000
b0 0
b1111 .
b1111 /
b1000 '
1"
#325000
0"
#330000
1"
#335000
0"
#340000
b111 .
b0 )
1"
#345000
0"
#350000
1"
#355000
0"
#360000
b1000 +
1-
b1000 #
b1000 *
b1000 0
b1100 )
1"
#365000
0"
#370000
b0 %
0-
b0 #
0!
b0 *
b1000 $
b0 0
b1111 .
b1000 )
b1000 1
1"
#375000
0"
#380000
1"
#385000
0"
#390000
1"
#395000
0"
#400000
1"
#405000
0"
#410000
b100 0
b1011 .
b1011 /
b1111 (
1"
#415000
0"
#420000
b0 0
b1111 .
b1111 /
b1000 (
1"
#425000
0"
#430000
b1 *
b1 0
b1110 .
b1100 &
1"
#435000
0"
#440000
b0 *
b0 0
b1111 .
b1000 &
1"
#445000
0"
#450000
b1101 .
b0 '
1"
#455000
0"
#460000
1-
b1000 #
b111 %
b1000 +
1!
b1000 *
b0 $
b1000 0
b101 .
b1100 )
1"
#465000
0"
#470000
b0 %
0!
0-
b0 #
b1000 $
b0 *
b1101 .
b10 0
b1101 /
b1000 )
b1101 '
1"
#475000
0"
#480000
b0 0
b1111 .
b1111 /
b1000 '
1"
#485000
0"
#490000
1"
#495000
0"
#500000
1"
#505000
0"
#510000
1"
#515000
0"
#520000
1"
#525000
0"
#530000
1"
#535000
0"
#540000
1"
#545000
0"
#550000
1"
#555000
0"
#560000
1"
#565000
0"
#570000
1"
#575000
0"
#580000
1"
#585000
0"
#590000
1"
#595000
0"
#600000
1"
#605000
0"
#610000
1"
#615000
0"
#620000
1"
#625000
0"
#630000
b1 0
b1110 .
b1110 /
b1110 &
1"
#635000
0"
#640000
b100 0
b1011 .
b1011 /
b1111 (
b1000 &
1"
#645000
0"
#650000
b0 0
b1111 .
b1111 /
b1000 (
1"
#655000
0"
#660000
1"
#665000
0"
#670000
1"
#675000
0"
#680000
b10 *
b10 0
b1101 .
b1100 '
1"
#685000
0"
#690000
b0 *
b0 0
b1111 .
b1000 '
1"
#695000
0"
#700000
1"
#705000
0"
#710000
b100 0
b1011 .
b1011 /
b1110 (
1"
#715000
0"
#720000
b0 0
b1111 .
b1111 /
b1000 (
1"
#725000
0"
#730000
1"
#735000
0"
#740000
1"
#745000
0"
#750000
1"
#755000
0"
#760000
b111 %
b0 +
1!
b0 $
b111 .
b0 )
1"
#765000
0"
#770000
b1000 0
b111 /
b1111 )
b0 1
1"
#775000
0"
#780000
b10 0
b1101 .
b1101 /
b1000 )
b1110 '
1"
#785000
0"
#790000
b0 0
b1111 .
b1111 /
b1000 '
1"
#795000
0"
#800000
1"
#805000
0"
#810000
1"
#815000
0"
#820000
b1 0
b1110 .
b1110 /
b1110 &
1"
#825000
0"
#830000
b0 0
b1111 .
b1111 /
b1000 &
1"
#835000
0"
#840000
1"
#845000
0"
#850000
1"
#855000
0"
#860000
1"
#865000
0"
#870000
1"
#875000
0"
#880000
b1101 .
b0 '
1"
#885000
0"
#890000
1"
#895000
0"
#900000
b1 %
b10 +
1-
b10 #
b10 *
b10 0
b1100 '
1"
#905000
0"
#910000
b0 %
0-
b0 #
0!
b0 *
b10 $
b0 0
b1111 .
b1000 '
b10 1
1"
#915000
0"
#920000
1"
#925000
0"
#930000
b100 0
b1011 .
b1011 /
b1110 (
1"
#935000
0"
#940000
b1 *
b1111 /
b1 0
b1110 .
b1000 (
b1100 &
1"
#945000
0"
#950000
b0 *
b0 0
b1111 .
b1000 &
1"
